DateTimeTZ/DateTimeTZ.py
DateTimeTZ/__init__.py
DateTimeTZ/version.py
robotframework_datetime_tz-1.0.6.dist-info/LICENSE
robotframework_datetime_tz-1.0.6.dist-info/METADATA
robotframework_datetime_tz-1.0.6.dist-info/WHEEL
robotframework_datetime_tz-1.0.6.dist-info/top_level.txt
robotframework_datetime_tz-1.0.6.dist-info/RECORD
