Metadata-Version: 2.1
Name: robotframework-datetime-tz
Version: 1.0.6
Summary: Robot Framework library for date/time with locales and time zones
Home-page: https://github.com/testautomation/DateTimeTZ
Author: Tset Noitamotua
Author-email: tset.no@gmail.com
License: Apache License 2.0
Keywords: robotframework test automation rpa library date time locales time-zones
Platform: UNKNOWN
Classifier: Development Status :: 2 - Pre-Alpha
Classifier: License :: OSI Approved :: Apache Software License
Classifier: Operating System :: POSIX
Classifier: Operating System :: OS Independent
Classifier: Programming Language :: Python
Classifier: Programming Language :: Python :: 2.7
Classifier: Programming Language :: Python :: 3.6
Classifier: Topic :: Software Development :: Testing
Classifier: Topic :: Software Development :: Quality Assurance
Classifier: Framework :: Robot Framework
Classifier: Framework :: Robot Framework :: Library
Classifier: Intended Audience :: Developers
Requires-Dist: pytz
Requires-Dist: six
Requires-Dist: python-dateutil
Requires-Dist: Babel
Requires-Dist: robotframework
